Metadata-Version: 2.1
Name: server-test
Version: 0.1
Summary: Server packet
Home-page: UNKNOWN
Author: Nikolai Nagornyi
Author-email: isp@mail.ru
License: UNKNOWN
Platform: UNKNOWN
